efb_qq_slave/ChatMgr.py
efb_qq_slave/ClientMgr.py
efb_qq_slave/CustomTypes.py
efb_qq_slave/__init__.py
efb_qq_slave/__version__.py
efb_qq_slave/Clients/BaseClient.py
efb_qq_slave/Clients/__init__.py
efb_qq_slave-2.0.1.dist-info/LICENSE
efb_qq_slave-2.0.1.dist-info/METADATA
efb_qq_slave-2.0.1.dist-info/WHEEL
efb_qq_slave-2.0.1.dist-info/entry_points.txt
efb_qq_slave-2.0.1.dist-info/top_level.txt
efb_qq_slave-2.0.1.dist-info/RECORD
